uccli/__init__.py
uccli/agent_communication.py
uccli/main.py
uccli-0.0.5.1.dist-info/METADATA
uccli-0.0.5.1.dist-info/WHEEL
uccli-0.0.5.1.dist-info/top_level.txt
uccli-0.0.5.1.dist-info/RECORD
