Metadata-Version: 2.1
Name: uccli
Version: 0.0.5.1
Summary: A small flexible CLI framework with state machine capabilities
Author: Rene Luijk
Author-email: rene.luijk@clic2connect.nl
Classifier: Programming Language :: Python :: 3
Classifier: License :: OSI Approved :: MIT License
Classifier: Operating System :: OS Independent
Requires-Python: >=3.6
Requires-Dist: cmd2>=2.0.0
Requires-Dist: prompt_toolkit>=3.0.0
Requires-Dist: typing-extensions>=4.0.0
Requires-Dist: graphviz
Requires-Dist: tabulate
Provides-Extra: dev
Requires-Dist: pytest>=6.0.0; extra == "dev"
Requires-Dist: pytest-asyncio>=0.14.0; extra == "dev"
